odoo/addons/sale_promotion_rule_display_discount_amount/README.rst
odoo/addons/sale_promotion_rule_display_discount_amount/__init__.py
odoo/addons/sale_promotion_rule_display_discount_amount/__manifest__.py
odoo/addons/sale_promotion_rule_display_discount_amount/i18n/sale_promotion_rule_display_discount_amount.pot
odoo/addons/sale_promotion_rule_display_discount_amount/models/__init__.py
odoo/addons/sale_promotion_rule_display_discount_amount/models/sale_order.py
odoo/addons/sale_promotion_rule_display_discount_amount/readme/CONTRIBUTORS.rst
odoo/addons/sale_promotion_rule_display_discount_amount/readme/DESCRIPTION.rst
odoo/addons/sale_promotion_rule_display_discount_amount/readme/USAGE.rst
odoo/addons/sale_promotion_rule_display_discount_amount/static/description/icon.png
odoo/addons/sale_promotion_rule_display_discount_amount/static/description/index.html
odoo/addons/sale_promotion_rule_display_discount_amount/tests/__init__.py
odoo/addons/sale_promotion_rule_display_discount_amount/tests/test_sale_order.py
odoo14_addon_sale_promotion_rule_display_discount_amount-14.0.1.0.1.dist-info/METADATA
odoo14_addon_sale_promotion_rule_display_discount_amount-14.0.1.0.1.dist-info/WHEEL
odoo14_addon_sale_promotion_rule_display_discount_amount-14.0.1.0.1.dist-info/top_level.txt
odoo14_addon_sale_promotion_rule_display_discount_amount-14.0.1.0.1.dist-info/RECORD
