Metadata-Version: 2.1
Name: odoo14-addon-sale-promotion-rule-display-discount-amount
Version: 14.0.1.0.1
Summary: This addon allows you to display the amount of the discount applied by the sale promotion rules on the sale order
Home-page: https://github.com/OCA/sale-workflow
Author: ACSONE SA/NV,Odoo Community Association (OCA)
Author-email: support@odoo-community.org
License: AGPL-3
Platform: UNKNOWN
Classifier: Programming Language :: Python
Classifier: Framework :: Odoo
Classifier: Framework :: Odoo :: 14.0
Classifier: License :: OSI Approved :: GNU Affero General Public License v3
Classifier: Development Status :: 4 - Beta
Requires-Python: >=3.6
Requires-Dist: odoo14-addon-sale-discount-display-amount
Requires-Dist: odoo14-addon-sale-promotion-rule
Requires-Dist: odoo (<14.1dev,>=14.0a)
